xara_mesh/__init__.py
xara_mesh/cytriangle/.github/workflows/ci.yaml
xara_mesh/cytriangle/.github/workflows/publish.yaml
xara_mesh/cytriangle/.gitignore
xara_mesh/cytriangle/.pre-commit-config.yaml
xara_mesh/cytriangle/LICENSE
xara_mesh/cytriangle/README.md
xara_mesh/cytriangle/build_ext.py
xara_mesh/cytriangle/poetry.lock
xara_mesh/cytriangle/pyproject.toml
xara_mesh/cytriangle/requirements.txt
xara_mesh/cytriangle/src/c/A.poly
xara_mesh/cytriangle/src/c/README
xara_mesh/cytriangle/src/c/makefile
xara_mesh/cytriangle/src/c/showme.c
xara_mesh/cytriangle/src/c/triangle.c
xara_mesh/cytriangle/src/c/triangle.h
xara_mesh/cytriangle/src/c/tricall.c
xara_mesh/cytriangle/src/cytriangle/__init__.py
xara_mesh/cytriangle/src/cytriangle/ctriangle.pxd
xara_mesh/cytriangle/src/cytriangle/cytriangle.c
xara_mesh/cytriangle/src/cytriangle/cytriangle.pyx
xara_mesh/cytriangle/src/cytriangle/cytriangleio.c
xara_mesh/cytriangle/src/cytriangle/cytriangleio.pxd
xara_mesh/cytriangle/src/cytriangle/cytriangleio.pyx
xara_mesh/cytriangle/tests/sample.py
xara_mesh/cytriangle/tests/test_cytriangle.py
xara_mesh/distance/__init__.py
xara_mesh/distance/geometry/__init__.py
xara_mesh/distance/geometry/circle.py
xara_mesh/distance/geometry/ellipse.py
xara_mesh/distance/geometry/geometry.py
xara_mesh/distance/geometry/halfspace.py
xara_mesh/distance/geometry/path.py
xara_mesh/distance/geometry/polygon.py
xara_mesh/distance/geometry/pypathlib/__init__.py
xara_mesh/distance/geometry/pypathlib/closed_path.py
xara_mesh/distance/geometry/pypathlib/helpers.py
xara_mesh/distance/geometry/pypathlib/path.py
xara_mesh/distance/geometry/rectangle.py
xara_mesh/distance/geometry/rotation.py
xara_mesh/distance/helpers.py
xara_mesh/distance/main.py
xara_mesh/schewchuk/__init__.py
xara_mesh/schewchuk/_triangle_ct.py
xara_mesh/schewchuk/core.py
xara_mesh/schewchuk/libtriangle_lib.dylib
xara_mesh/schewchuk/trio.py
xara_mesh/simplex/__init__.py
xara_mesh/simplex/_exceptions.py
xara_mesh/simplex/_helpers.py
xara_mesh-0.0.3.dist-info/METADATA
xara_mesh-0.0.3.dist-info/WHEEL
xara_mesh-0.0.3.dist-info/entry_points.txt
xara_mesh-0.0.3.dist-info/RECORD
