Metadata-Version: 2.2
Name: xara_mesh
Version: 0.0.3
Summary: Meshing utilities for xara.
Keywords: pre-processing,finite-element-analysis,xara,opensees,openseespy,meshing,2D
Author-Email: Wensley Rushing <50180406+wensley-rushing@users.noreply.github.com>
Classifier: Development Status :: 5 - Production/Stable
Classifier: Intended Audience :: Science/Research
Classifier: Intended Audience :: Developers
Classifier: License :: OSI Approved :: GNU General Public License v3 or later (GPLv3+)
Classifier: Programming Language :: C
Classifier: Programming Language :: Python
Classifier: Programming Language :: Python :: 3
Classifier: Programming Language :: Python :: 3.8
Classifier: Programming Language :: Python :: 3.9
Classifier: Programming Language :: Python :: 3.10
Classifier: Programming Language :: Python :: 3.11
Classifier: Programming Language :: Python :: 3.12
Classifier: Programming Language :: Python :: 3 :: Only
Classifier: Topic :: Software Development
Classifier: Topic :: Scientific/Engineering
Classifier: Operating System :: Microsoft :: Windows
Classifier: Operating System :: POSIX
Classifier: Operating System :: Unix
Classifier: Operating System :: MacOS
Project-URL: Repository, https://github.com/wensley-rushing/
Requires-Dist: opensees
Requires-Dist: pyyaml
Requires-Dist: scipy
Requires-Dist: numpy
Requires-Dist: npx
Requires-Dist: xara
Requires-Dist: matplotlib
Requires-Dist: shps>=0.0.26
